remediation_exploits_enumeration/__init__.py
remediation_exploits_enumeration/capec/__init__.py
remediation_exploits_enumeration/exploitation_difficulty/__init__.py
remediation_exploits_enumeration/remediation_efforts/__init__.py
remediation_exploits_enumeration-1.1.2.dist-info/METADATA
remediation_exploits_enumeration-1.1.2.dist-info/WHEEL
remediation_exploits_enumeration-1.1.2.dist-info/top_level.txt
remediation_exploits_enumeration-1.1.2.dist-info/RECORD
