Metadata-Version: 2.1
Name: remediation-exploits-enumeration
Version: 1.1.2
Summary: remediation_exploits_enumeration
Home-page: https://github.com/m4l1c3/remediation_exploits_enumeration
Author: m4l1c3
Author-email: m4l1c3@protonmail.com
License: UNKNOWN
Platform: UNKNOWN
Classifier: Programming Language :: Python :: 3
Classifier: License :: OSI Approved :: MIT License
Classifier: Operating System :: OS Independent
